tkreform/__init__.py
tkreform/base.py
tkreform/declarative.py
tkreform/events.py
tkreform/exceptions.py
tkreform/groups.py
tkreform/menu.py
tkreform-0.3.6.dist-info/LICENSE
tkreform-0.3.6.dist-info/METADATA
tkreform-0.3.6.dist-info/WHEEL
tkreform-0.3.6.dist-info/top_level.txt
tkreform-0.3.6.dist-info/RECORD
