Metadata-Version: 2.1
Name: tkreform
Version: 0.3.6
Summary: Reformed tkinter coding tool.
Home-page: https://github.com/tkinguist/tkreform
Author: HivertMoZara
Author-email: worldmozara@gmail.com
License: MIT
Platform: UNKNOWN
Classifier: Development Status :: 3 - Alpha
Classifier: Intended Audience :: Developers
Classifier: License :: OSI Approved :: MIT License
Classifier: Programming Language :: Python :: 3
Classifier: Programming Language :: Python :: 3.7
Classifier: Programming Language :: Python :: 3.8
Classifier: Programming Language :: Python :: 3.9
Classifier: Programming Language :: Python :: 3.10
Classifier: Programming Language :: Python :: 3.11
Requires-Python: >=3.7
License-File: LICENSE
Requires-Dist: typing-extensions (<5,>=4.0)
Provides-Extra: pil
Requires-Dist: Pillow (>=2.7) ; extra == 'pil'
